LICENSE
README.md
setup.py
eessi/cli/init.py
eessi/cli/main.py
eessi_cli.egg-info/PKG-INFO
eessi_cli.egg-info/SOURCES.txt
eessi_cli.egg-info/dependency_links.txt
eessi_cli.egg-info/entry_points.txt
eessi_cli.egg-info/requires.txt
eessi_cli.egg-info/top_level.txt