Metadata-Version: 2.1
Name: eessi-cli
Version: 0.0.1
Summary: EESSI command line interface
Home-page: https://github.com/EESSI/eessi-cli
Requires-Python: >=3.6
License-File: LICENSE
Requires-Dist: click>=8.0
